{
  "annotations": {
    "list": [
      {
        "builtIn": 1,
        "datasource": { "type": "grafana", "uid": "-- Grafana --" },
        "enable": true,
        "hide": true,
        "iconColor": "rgba(0, 211, 255, 1)",
        "name": "Annotations & Alerts",
        "type": "dashboard"
      }
    ]
  },
  "editable": true,
  "fiscalYearStartMonth": 0,
  "graphTooltip": 1,
  "id": null,
  "links": [],
  "liveNow": false,
  "panels": [
    {
      "collapsed": false,
      "gridPos": { "h": 1, "w": 24, "x": 0, "y": 0 },
      "id": 100,
      "panels": [],
      "title": "API Performance",
      "type": "row"
    },
    {
      "datasource": { "type": "prometheus", "uid": "prometheus" },
      "fieldConfig": {
        "defaults": {
          "color": { "mode": "palette-classic" },
          "custom": {
            "axisCenteredZero": false,
            "axisColorMode": "text",
            "axisLabel": "Requests/sec",
            "axisPlacement": "auto",
            "barAlignment": 0,
            "drawStyle": "line",
            "fillOpacity": 10,
            "gradientMode": "none",
            "hideFrom": { "tooltip": false, "viz": false, "legend": false },
            "lineInterpolation": "smooth",
            "lineWidth": 2,
            "pointSize": 5,
            "scaleDistribution": { "type": "linear" },
            "showPoints": "never",
            "spanNulls": false,
            "stacking": { "group": "A", "mode": "none" },
            "thresholdsStyle": { "mode": "off" }
          },
          "mappings": [],
          "thresholds": {
            "mode": "absolute",
            "steps": [
              { "color": "green", "value": null }
            ]
          },
          "unit": "reqps"
        }
      },
      "gridPos": { "h": 8, "w": 12, "x": 0, "y": 1 },
      "id": 1,
      "options": {
        "legend": { "calcs": ["mean", "max"], "displayMode": "table", "placement": "bottom" },
        "tooltip": { "mode": "multi", "sort": "desc" }
      },
      "targets": [
        {
          "expr": "rate(http_requests_total{job=\"dmarc-backend\"}[5m])",
          "legendFormat": "{{method}} {{endpoint}}",
          "refId": "A"
        }
      ],
      "title": "API Request Rate",
      "type": "timeseries"
    },
    {
      "datasource": { "type": "prometheus", "uid": "prometheus" },
      "fieldConfig": {
        "defaults": {
          "color": { "mode": "palette-classic" },
          "custom": {
            "axisCenteredZero": false,
            "axisColorMode": "text",
            "axisLabel": "Latency (ms)",
            "axisPlacement": "auto",
            "barAlignment": 0,
            "drawStyle": "line",
            "fillOpacity": 10,
            "gradientMode": "none",
            "hideFrom": { "tooltip": false, "viz": false, "legend": false },
            "lineInterpolation": "smooth",
            "lineWidth": 2,
            "pointSize": 5,
            "scaleDistribution": { "type": "linear" },
            "showPoints": "never",
            "spanNulls": false,
            "stacking": { "group": "A", "mode": "none" },
            "thresholdsStyle": { "mode": "off" }
          },
          "mappings": [],
          "thresholds": {
            "mode": "absolute",
            "steps": [
              { "color": "green", "value": null },
              { "color": "yellow", "value": 500 },
              { "color": "red", "value": 1000 }
            ]
          },
          "unit": "ms"
        }
      },
      "gridPos": { "h": 8, "w": 12, "x": 12, "y": 1 },
      "id": 2,
      "options": {
        "legend": { "calcs": ["mean", "max", "p95"], "displayMode": "table", "placement": "bottom" },
        "tooltip": { "mode": "multi", "sort": "desc" }
      },
      "targets": [
        {
          "expr": "histogram_quantile(0.50, rate(http_request_duration_seconds_bucket{job=\"dmarc-backend\"}[5m])) * 1000",
          "legendFormat": "p50",
          "refId": "A"
        },
        {
          "expr": "histogram_quantile(0.95, rate(http_request_duration_seconds_bucket{job=\"dmarc-backend\"}[5m])) * 1000",
          "legendFormat": "p95",
          "refId": "B"
        },
        {
          "expr": "histogram_quantile(0.99, rate(http_request_duration_seconds_bucket{job=\"dmarc-backend\"}[5m])) * 1000",
          "legendFormat": "p99",
          "refId": "C"
        }
      ],
      "title": "API Latency (Percentiles)",
      "type": "timeseries"
    },
    {
      "datasource": { "type": "prometheus", "uid": "prometheus" },
      "fieldConfig": {
        "defaults": {
          "color": { "mode": "palette-classic" },
          "custom": {
            "axisCenteredZero": false,
            "axisColorMode": "text",
            "axisLabel": "Error Rate",
            "axisPlacement": "auto",
            "barAlignment": 0,
            "drawStyle": "line",
            "fillOpacity": 10,
            "gradientMode": "none",
            "hideFrom": { "tooltip": false, "viz": false, "legend": false },
            "lineInterpolation": "smooth",
            "lineWidth": 2,
            "pointSize": 5,
            "scaleDistribution": { "type": "linear" },
            "showPoints": "never",
            "spanNulls": false,
            "stacking": { "group": "A", "mode": "none" },
            "thresholdsStyle": { "mode": "off" }
          },
          "mappings": [],
          "thresholds": {
            "mode": "absolute",
            "steps": [
              { "color": "green", "value": null },
              { "color": "yellow", "value": 0.01 },
              { "color": "red", "value": 0.05 }
            ]
          },
          "unit": "percentunit"
        }
      },
      "gridPos": { "h": 8, "w": 12, "x": 0, "y": 9 },
      "id": 3,
      "options": {
        "legend": { "calcs": ["mean", "max"], "displayMode": "table", "placement": "bottom" },
        "tooltip": { "mode": "multi", "sort": "desc" }
      },
      "targets": [
        {
          "expr": "sum(rate(http_requests_total{job=\"dmarc-backend\",status=~\"5..\"}[5m])) / sum(rate(http_requests_total{job=\"dmarc-backend\"}[5m]))",
          "legendFormat": "5xx Error Rate",
          "refId": "A"
        },
        {
          "expr": "sum(rate(http_requests_total{job=\"dmarc-backend\",status=~\"4..\"}[5m])) / sum(rate(http_requests_total{job=\"dmarc-backend\"}[5m]))",
          "legendFormat": "4xx Error Rate",
          "refId": "B"
        }
      ],
      "title": "API Error Rates",
      "type": "timeseries"
    },
    {
      "collapsed": false,
      "gridPos": { "h": 1, "w": 24, "x": 0, "y": 17 },
      "id": 200,
      "panels": [],
      "title": "Database Health",
      "type": "row"
    },
    {
      "datasource": { "type": "prometheus", "uid": "prometheus" },
      "fieldConfig": {
        "defaults": {
          "color": { "mode": "thresholds" },
          "mappings": [],
          "thresholds": {
            "mode": "absolute",
            "steps": [
              { "color": "green", "value": null },
              { "color": "yellow", "value": 50 },
              { "color": "red", "value": 80 }
            ]
          },
          "unit": "short"
        }
      },
      "gridPos": { "h": 4, "w": 6, "x": 0, "y": 18 },
      "id": 4,
      "options": {
        "colorMode": "value",
        "graphMode": "area",
        "justifyMode": "auto",
        "orientation": "auto",
        "reduceOptions": { "calcs": ["lastNotNull"], "fields": "", "values": false },
        "textMode": "auto"
      },
      "targets": [
        {
          "expr": "pg_stat_database_numbackends{datname=\"dmarc\"}",
          "refId": "A"
        }
      ],
      "title": "DB Active Connections",
      "type": "stat"
    },
    {
      "datasource": { "type": "prometheus", "uid": "prometheus" },
      "fieldConfig": {
        "defaults": {
          "color": { "mode": "thresholds" },
          "mappings": [],
          "thresholds": {
            "mode": "absolute",
            "steps": [
              { "color": "green", "value": null }
            ]
          },
          "unit": "bytes"
        }
      },
      "gridPos": { "h": 4, "w": 6, "x": 6, "y": 18 },
      "id": 5,
      "options": {
        "colorMode": "value",
        "graphMode": "area",
        "justifyMode": "auto",
        "orientation": "auto",
        "reduceOptions": { "calcs": ["lastNotNull"], "fields": "", "values": false },
        "textMode": "auto"
      },
      "targets": [
        {
          "expr": "pg_database_size_bytes{datname=\"dmarc\"}",
          "refId": "A"
        }
      ],
      "title": "Database Size",
      "type": "stat"
    },
    {
      "datasource": { "type": "prometheus", "uid": "prometheus" },
      "fieldConfig": {
        "defaults": {
          "color": { "mode": "palette-classic" },
          "custom": {
            "axisCenteredZero": false,
            "axisColorMode": "text",
            "axisLabel": "Queries/sec",
            "axisPlacement": "auto",
            "barAlignment": 0,
            "drawStyle": "line",
            "fillOpacity": 10,
            "gradientMode": "none",
            "hideFrom": { "tooltip": false, "viz": false, "legend": false },
            "lineInterpolation": "smooth",
            "lineWidth": 2,
            "pointSize": 5,
            "scaleDistribution": { "type": "linear" },
            "showPoints": "never",
            "spanNulls": false,
            "stacking": { "group": "A", "mode": "none" },
            "thresholdsStyle": { "mode": "off" }
          },
          "mappings": [],
          "thresholds": {
            "mode": "absolute",
            "steps": [
              { "color": "green", "value": null }
            ]
          },
          "unit": "short"
        }
      },
      "gridPos": { "h": 8, "w": 12, "x": 12, "y": 18 },
      "id": 6,
      "options": {
        "legend": { "calcs": ["mean"], "displayMode": "list", "placement": "bottom" },
        "tooltip": { "mode": "multi", "sort": "desc" }
      },
      "targets": [
        {
          "expr": "rate(pg_stat_database_xact_commit{datname=\"dmarc\"}[5m])",
          "legendFormat": "Commits",
          "refId": "A"
        },
        {
          "expr": "rate(pg_stat_database_xact_rollback{datname=\"dmarc\"}[5m])",
          "legendFormat": "Rollbacks",
          "refId": "B"
        }
      ],
      "title": "Database Transaction Rate",
      "type": "timeseries"
    },
    {
      "collapsed": false,
      "gridPos": { "h": 1, "w": 24, "x": 0, "y": 26 },
      "id": 300,
      "panels": [],
      "title": "Redis Cache",
      "type": "row"
    },
    {
      "datasource": { "type": "prometheus", "uid": "prometheus" },
      "fieldConfig": {
        "defaults": {
          "color": { "mode": "thresholds" },
          "mappings": [],
          "thresholds": {
            "mode": "absolute",
            "steps": [
              { "color": "green", "value": null },
              { "color": "yellow", "value": 70 },
              { "color": "red", "value": 90 }
            ]
          },
          "unit": "percent"
        }
      },
      "gridPos": { "h": 4, "w": 6, "x": 0, "y": 27 },
      "id": 7,
      "options": {
        "colorMode": "value",
        "graphMode": "area",
        "justifyMode": "auto",
        "orientation": "auto",
        "reduceOptions": { "calcs": ["lastNotNull"], "fields": "", "values": false },
        "textMode": "auto"
      },
      "targets": [
        {
          "expr": "redis_memory_used_bytes / redis_memory_max_bytes * 100",
          "refId": "A"
        }
      ],
      "title": "Redis Memory Usage",
      "type": "stat"
    },
    {
      "datasource": { "type": "prometheus", "uid": "prometheus" },
      "fieldConfig": {
        "defaults": {
          "color": { "mode": "thresholds" },
          "mappings": [],
          "thresholds": {
            "mode": "absolute",
            "steps": [
              { "color": "green", "value": null }
            ]
          },
          "unit": "short"
        }
      },
      "gridPos": { "h": 4, "w": 6, "x": 6, "y": 27 },
      "id": 8,
      "options": {
        "colorMode": "value",
        "graphMode": "area",
        "justifyMode": "auto",
        "orientation": "auto",
        "reduceOptions": { "calcs": ["lastNotNull"], "fields": "", "values": false },
        "textMode": "auto"
      },
      "targets": [
        {
          "expr": "redis_connected_clients",
          "refId": "A"
        }
      ],
      "title": "Redis Connected Clients",
      "type": "stat"
    },
    {
      "datasource": { "type": "prometheus", "uid": "prometheus" },
      "fieldConfig": {
        "defaults": {
          "color": { "mode": "palette-classic" },
          "custom": {
            "axisCenteredZero": false,
            "axisColorMode": "text",
            "axisLabel": "",
            "axisPlacement": "auto",
            "barAlignment": 0,
            "drawStyle": "line",
            "fillOpacity": 10,
            "gradientMode": "none",
            "hideFrom": { "tooltip": false, "viz": false, "legend": false },
            "lineInterpolation": "smooth",
            "lineWidth": 2,
            "pointSize": 5,
            "scaleDistribution": { "type": "linear" },
            "showPoints": "never",
            "spanNulls": false,
            "stacking": { "group": "A", "mode": "none" },
            "thresholdsStyle": { "mode": "off" }
          },
          "mappings": [],
          "thresholds": {
            "mode": "absolute",
            "steps": [
              { "color": "green", "value": null }
            ]
          },
          "unit": "ops"
        }
      },
      "gridPos": { "h": 8, "w": 12, "x": 12, "y": 27 },
      "id": 9,
      "options": {
        "legend": { "calcs": ["mean"], "displayMode": "list", "placement": "bottom" },
        "tooltip": { "mode": "multi", "sort": "desc" }
      },
      "targets": [
        {
          "expr": "rate(redis_commands_total[5m])",
          "legendFormat": "{{cmd}}",
          "refId": "A"
        }
      ],
      "title": "Redis Commands Rate",
      "type": "timeseries"
    }
  ],
  "refresh": "30s",
  "schemaVersion": 38,
  "style": "dark",
  "tags": ["dmarc", "system-health"],
  "templating": { "list": [] },
  "time": { "from": "now-1h", "to": "now" },
  "timepicker": {},
  "timezone": "",
  "title": "DMARC Dashboard - System Health",
  "uid": "dmarc-system-health",
  "version": 1,
  "weekStart": ""
}
